setup.cfg
setup.py
rabbitadmin/__init__.py
rabbitadmin/client.py
rabbitadmin/http.py
rabbitadmin.egg-info/PKG-INFO
rabbitadmin.egg-info/SOURCES.txt
rabbitadmin.egg-info/dependency_links.txt
rabbitadmin.egg-info/requires.txt
rabbitadmin.egg-info/top_level.txt