Metadata-Version: 1.1
Name: rabbitadmin
Version: 1.2.1
Summary: A simple rabbitmq management module, autogenerated from the documentation
Home-page: https://github.com/Taywee/rabbitadmin
Author: Taylor C. Richberger <tcr@absolute-performance.com>
Author-email: tcr@absolute-performance.com
License: MIT
Download-URL: https://github.com/Taywee/rabbitadmin
Keywords: python http amqp rabbit rabbitmq management
Platform: UNKNOWN
Classifier: Intended Audience :: Developers
Classifier: License :: OSI Approved :: MIT License
Classifier: Natural Language :: English
Classifier: Programming Language :: Python
Classifier: Programming Language :: Python :: 2
Classifier: Programming Language :: Python :: 2.7
Classifier: Programming Language :: Python :: 3
Classifier: Programming Language :: Python :: 3.5
Classifier: Topic :: Internet :: WWW/HTTP
Classifier: Topic :: Software Development :: Libraries :: Python Modules
